pypet/__init__.py
pypet/alias_manager.py
pypet/config.py
pypet/models.py
pypet/storage.py
pypet/sync.py
pypet/cli/__init__.py
pypet/cli/alias_commands.py
pypet/cli/execution_commands.py
pypet/cli/main.py
pypet/cli/save_commands.py
pypet/cli/snippet_commands.py
pypet/cli/sync_commands.py
pypet_cli-0.5.1.dist-info/METADATA
pypet_cli-0.5.1.dist-info/WHEEL
pypet_cli-0.5.1.dist-info/entry_points.txt
pypet_cli-0.5.1.dist-info/licenses/LICENSE
pypet_cli-0.5.1.dist-info/RECORD
