Metadata-Version: 2.4
Name: pypet-cli
Version: 0.5.1
Summary: A modern command-line snippet manager with Git synchronization, clipboard integration, and parameterized commands
Project-URL: Homepage, https://github.com/fabiandistler/pypet
Project-URL: Repository, https://github.com/fabiandistler/pypet.git
Project-URL: Issues, https://github.com/fabiandistler/pypet/issues
Project-URL: Changelog, https://github.com/fabiandistler/pypet/blob/main/CHANGELOG.md
Author-email: Fabian Distler <fabian@distler.dev>
License: MIT
License-File: LICENSE
Keywords: cli,clipboard,commands,git,productivity,shell,snippets
Classifier: Development Status :: 4 - Beta
Classifier: Environment :: Console
Classifier: Intended Audience :: Developers
Classifier: Intended Audience :: System Administrators
Classifier: License :: OSI Approved :: MIT License
Classifier: Operating System :: OS Independent
Classifier: Programming Language :: Python :: 3
Classifier: Programming Language :: Python :: 3.10
Classifier: Programming Language :: Python :: 3.11
Classifier: Programming Language :: Python :: 3.12
Classifier: Topic :: Software Development :: Libraries :: Python Modules
Classifier: Topic :: System :: Systems Administration
Classifier: Topic :: Utilities
Classifier: Typing :: Typed
Requires-Python: >=3.10
Requires-Dist: click>=8.1.7
Requires-Dist: gitpython>=3.1.40
Requires-Dist: pyperclip>=1.9.0
Requires-Dist: rich>=13.7.0
Requires-Dist: toml>=0.10.2
Provides-Extra: dev
Requires-Dist: black>=24.0.0; extra == 'dev'
Requires-Dist: pytest-cov>=5.0.0; extra == 'dev'
Requires-Dist: pytest>=8.4.0; extra == 'dev'
Requires-Dist: ruff>=0.1.0; extra == 'dev'
